integration_tests/__init__.py
integration_tests/pil_test.py
integration_tests/urls_helpers.py
opencv_engine/__init__.py
opencv_engine/engine.py
tests/__init__.py
tests/integration/__init__.py
tests/integration/opencv_test.py
tests/unit/__init__.py
thumbor_engine_opencv/__init__.py
thumbor_engine_opencv/engine.py
thumbor_engine_opencv-1.0.0.dist-info/DESCRIPTION.rst
thumbor_engine_opencv-1.0.0.dist-info/METADATA
thumbor_engine_opencv-1.0.0.dist-info/RECORD
thumbor_engine_opencv-1.0.0.dist-info/WHEEL
thumbor_engine_opencv-1.0.0.dist-info/metadata.json
thumbor_engine_opencv-1.0.0.dist-info/top_level.txt
