Metadata-Version: 2.0
Name: thumbor-engine-opencv
Version: 1.0.0
Summary: OpenCV imaging engine for thumbor.
Home-page: https://github.com/DogParkLabs/thumbor_engine_opencv/
Author: Dog Park Labs
Author-email: patmcgee@dogparklabs.com
License: MIT
Keywords: thumbor imaging opencv
Platform: UNKNOWN
Classifier: Development Status :: 4 - Beta
Classifier: Intended Audience :: Developers
Classifier: License :: OSI Approved :: MIT License
Classifier: Natural Language :: English
Classifier: Operating System :: MacOS
Classifier: Operating System :: POSIX
Classifier: Operating System :: Unix
Classifier: Operating System :: OS Independent
Classifier: Programming Language :: Python :: 2.7
Classifier: Topic :: Multimedia :: Graphics
Provides-Extra: tests
Requires-Dist: colour
Requires-Dist: numpy
Requires-Dist: thumbor
Requires-Dist: opencv-python
Requires-Dist: pexif
Provides-Extra: tests
Requires-Dist: mock; extra == 'tests'
Requires-Dist: nose; extra == 'tests'
Requires-Dist: yanc; extra == 'tests'
Requires-Dist: colorama; extra == 'tests'
Requires-Dist: preggy; extra == 'tests'
Requires-Dist: ipdb; extra == 'tests'
Requires-Dist: numpy; extra == 'tests'
Requires-Dist: colour; extra == 'tests'
